appearance/__init__.py
appearance/__main__.py
appearance/app.py
appearance/argparser.py
appearance/consts.py
appearance/helpers.py
appearance/service.py
appearance/validators.py
resources/__init__.py
resources/common_char.dat
resources/header.dat
resources/mb_characters_bytes.png
resources/backups/empty.txt
mb_app-0.0.7.dist-info/LICENSE
mb_app-0.0.7.dist-info/METADATA
mb_app-0.0.7.dist-info/WHEEL
mb_app-0.0.7.dist-info/entry_points.txt
mb_app-0.0.7.dist-info/top_level.txt
mb_app-0.0.7.dist-info/RECORD
