Metadata-Version: 2.1
Name: mb-app
Version: 0.0.7
Summary: Python util for Mount&Blade characters file manipulation.
Home-page: https://github.com/doppelmarker/mb_appearance
Author: doppelmarker
Author-email: doppelmarker@gmail.com
License: MIT
Classifier: Programming Language :: Python :: 3.8
Requires-Python: >=3.8
License-File: LICENSE
